{
  "type": "GeologicalModel",
  "groups": { "Surface Geology": [
                 {
                   "type": "ImagePlane",
                   "position": [868000.0, 6848000.0, 1001.0],
                   "model_url": "2MsurfaceGeologyZ52.PNG",
                   "display_name": "2M Surface Geology",
                   "include": true,
                   "displayed": true,
                   "reference": "http://www.minerals.statedevelopment.sa.gov.au/geoscience/geology/gawler_craton",
                   "3dobject_label": "2M Surface Geology"
                 }
              ],
              
              "Magnetism": [
                 {
                   "type": "ImagePlane",
                   "position": [868000.0, 6848000.0, 1002.0],
                   "model_url": "TMI_RTP.PNG",
                   "display_name": "Total Magnetic Intensity - RTP",
                   "include": true,
                   "displayed": true,
                   "reference": "https://sarigbasis.pir.sa.gov.au/WebtopEw/ws/samref/sarig1/image/DDD/GDP00026.pdf#page=5",
                   "3dobject_label": "Total Magnetic Intensity - RTP"
                 }
              ],
              
              "Gravity": [
                 {
                   "type": "ImagePlane",
                   "position": [868000.0, 6848000.0, 1003.0],
                   "model_url": "BougGrav.PNG",
                   "display_name": "Bouguer Gravity",
                   "include": true,
                   "displayed": true,
                   "reference": "https://sarigbasis.pir.sa.gov.au/WebtopEw/ws/samref/sarig1/image/DDD/GDP00026.pdf#page=5",
                   "3dobject_label": "Bouguer Gravity"
                 }
              ],
              
              "WMS": [
                 {
                   "type": "WMSLayer",
                   "position": [868000.0, 6848000.0, 100.0],
                   "model_url": "http://services.ga.gov.au/site_11/services/Global_Map_Project_Australian_Base_Map/MapServer/WMSServer",
                   "name": "Elevation",
                   "version": "1.3.0",
                   "id": "wms_imagery",
                   "display_name": "Australian Base Map",
                   "include": false,
                   "displayed": true,
                   "reference": "https://sarigbasis.pir.sa.gov.au/WebtopEw/ws/samref/sarig1/image/DDD/GDP00026.pdf#page=2"
                 }
              ],
              
              "Drapes": [
                 { 
                   "type": "GLTFObject",
                   "model_url": "2_Basement_Fixed.gltf",
                   "display_name": "Depth to basement",
                   "include": true,
                   "displayed": false,
                   "reference": "https://sarigbasis.pir.sa.gov.au/WebtopEw/ws/samref/sarig1/image/DDD/GDP00026.pdf#page=2"
                 },
                 {
                   "type": "GLTFObject",
                   "model_url": "MarlaOutline.gltf",
                   "display_name": "Marla Outline",
                   "include": true,
                   "displayed": false,
                   "reference": "https://sarigbasis.pir.sa.gov.au/WebtopEw/ws/samref/sarig1/image/DDD/GDP00026.pdf#page=2"
                 },
                 {
                   "type": "GLTFObject",
                   "model_url": "CP_Surface_Fixed.gltf",
                   "display_name": "Base of Carboniferous",
                   "include": true,
                   "displayed": false,
                   "reference": "https://sarigbasis.pir.sa.gov.au/WebtopEw/ws/samref/sarig1/image/DDD/GDP00026.pdf#page=2"
                 },
                 {
                   "type": "GLTFObject",
                   "model_url": "GravDrape.gltf",
                   "display_name": "Gravity Drape",
                   "include": true,
                   "displayed": false,
                   "reference": "https://sarigbasis.pir.sa.gov.au/WebtopEw/ws/samref/sarig1/image/DDD/GDP00026.pdf#page=2"
                 },
                 {
                   "type": "GLTFObject",
                   "model_url": "MagDrape.gltf",
                   "display_name": "Magnetic Drape",
                   "include": true,
                   "displayed": false,
                   "reference": "https://sarigbasis.pir.sa.gov.au/WebtopEw/ws/samref/sarig1/image/DDD/GDP00026.pdf#page=2"
                 },
                 {
                   "type": "GLTFObject",
                   "model_url": "SRTM_surf.gltf",
                   "display_name": "SRTM surface topology",
                   "include": true,
                   "displayed": false,
                   "reference": "https://sarigbasis.pir.sa.gov.au/WebtopEw/ws/samref/sarig1/image/DDD/GDP00026.pdf#page=2"
                 },
                 {
                   "type": "GLTFObject",
                   "model_url": "VOL_0.gltf",
                   "display_name": "VOI Marla",
                   "include": true,
                   "displayed": false,
                   "reference": "https://sarigbasis.pir.sa.gov.au/WebtopEw/ws/samref/sarig1/image/DDD/GDP00026.pdf#page=2"
                 },
                 {
                   "skip": true,
                   "type": "GLTFObject",
                   "model_url": "VOL_1.gltf",
                   "display_name": "VOL Marla Region Cut",
                   "include": false,
                   "displayed": false,
                   "reference": "https://sarigbasis.pir.sa.gov.au/WebtopEw/ws/samref/sarig1/image/DDD/GDP00026.pdf#page=2"
                 }
              ],
              
              "UBC": [
                 {
                   "type": "GLTFObject",
                   "model_url": "UBC_Basement.gltf",
                   "display_name": "UBC Basement Input",
                   "include": true,
                   "displayed": true,
                   "reference": "https://sarigbasis.pir.sa.gov.au/WebtopEw/ws/samref/sarig1/image/DDD/GDP00026.pdf#page=2"
                 }
              ],
              
              "UBC Density Isosurfaces": [
                 {
                   "type": "GLTFObject",
                   "model_url": "UBC_Density_neg_pt04.gltf",
                   "display_name": "-0.04g/cc",
                   "include": true,
                   "displayed": true,
                   "reference": "https://sarigbasis.pir.sa.gov.au/WebtopEw/ws/samref/sarig1/image/DDD/GDP00026.pdf#page=2"
                 },
                 {
                   "type": "GLTFObject",
                   "model_url": "UBC_Density_neg_pt08.gltf",
                   "display_name": "-0.08g/cc",
                   "include": true,
                   "displayed": true,
                   "reference": "https://sarigbasis.pir.sa.gov.au/WebtopEw/ws/samref/sarig1/image/DDD/GDP00026.pdf#page=2"
                 },
                 {
                   "type": "GLTFObject",
                   "model_url": "UBC_Density_neg_pt3.gltf",
                   "display_name": "-0.30g/cc",
                   "include": true,
                   "displayed": true,
                   "reference": "https://sarigbasis.pir.sa.gov.au/WebtopEw/ws/samref/sarig1/image/DDD/GDP00026.pdf#page=2"
                 },
                 {
                   "type": "GLTFObject",
                   "model_url": "UBC_Density_oZero.gltf",
                   "display_name": "0.00g/cc",
                   "include": true,
                   "displayed": true,
                   "reference": "https://sarigbasis.pir.sa.gov.au/WebtopEw/ws/samref/sarig1/image/DDD/GDP00026.pdf#page=2"
                 },
                 {
                   "type": "GLTFObject",
                   "model_url": "UBC_Density_pos_pt01.gltf",
                   "display_name": "0.01g/cc",
                   "include": true,
                   "displayed": true,
                   "reference": "https://sarigbasis.pir.sa.gov.au/WebtopEw/ws/samref/sarig1/image/DDD/GDP00026.pdf#page=2"
                 },
                 {
                   "type": "GLTFObject",
                   "model_url": "UBC_Density_pos_pt04.gltf",
                   "display_name": "0.04g/cc",
                   "include": true,
                   "displayed": true,
                   "reference": "https://sarigbasis.pir.sa.gov.au/WebtopEw/ws/samref/sarig1/image/DDD/GDP00026.pdf#page=2"
                 },
                 {
                   "type": "GLTFObject",
                   "model_url": "UBC_Density_pos_pt08.gltf",
                   "display_name": "0.08g/cc",
                   "include": true,
                   "displayed": true,
                   "reference": "https://sarigbasis.pir.sa.gov.au/WebtopEw/ws/samref/sarig1/image/DDD/GDP00026.pdf#page=2"
                 }
              ],
              "UBC Gravity": [
                 {
                   "type": "GLTFObject",
                   "model_url": "UBC_GravObs.gltf",
                   "display_name": "UBC Gravity Observations",
                   "include": true,
                   "displayed": true,
                   "reference": "https://sarigbasis.pir.sa.gov.au/WebtopEw/ws/samref/sarig1/image/DDD/GDP00026.pdf#page=2"
                 }
              ],
              "UBC Magnetism": [
                 {
                   "type": "GLTFObject",
                   "model_url": "UBC_MagObs.gltf",
                   "display_name": "UBC Magnetic Observations",
                   "include": true,
                   "displayed": true,
                   "reference": "https://sarigbasis.pir.sa.gov.au/WebtopEw/ws/samref/sarig1/image/DDD/GDP00026.pdf#page=2"
                 }
              ],
              "UBC Susceptibility Isosurfaces": [
                 {
                   "type": "GLTFObject",
                   "model_url": "UBC_Susc_0_0001.gltf",
                   "display_name": "0.0001 SI",
                   "include": true,
                   "displayed": true,
                   "reference": "https://sarigbasis.pir.sa.gov.au/WebtopEw/ws/samref/sarig1/image/DDD/GDP00026.pdf#page=2"
                 },
                 {
                   "type": "GLTFObject",
                   "model_url": "UBC_Susc_0_0010.gltf",
                   "display_name": "0.001 SI",
                   "include": true,
                   "displayed": true,
                   "reference": "https://sarigbasis.pir.sa.gov.au/WebtopEw/ws/samref/sarig1/image/DDD/GDP00026.pdf#page=2"
                 },
                 {
                   "type": "GLTFObject",
                   "model_url": "UBC_Susc_0_0100.gltf",
                   "display_name": "0.01 SI",
                   "include": true,
                   "displayed": true,
                   "reference": "https://sarigbasis.pir.sa.gov.au/WebtopEw/ws/samref/sarig1/image/DDD/GDP00026.pdf#page=2"
                 },
                 {
                   "type": "GLTFObject",
                   "model_url": "UBC_Susc_0_0200.gltf",
                   "display_name": "0.02 SI",
                   "include": true,
                   "displayed": true,
                   "reference": "https://sarigbasis.pir.sa.gov.au/WebtopEw/ws/samref/sarig1/image/DDD/GDP00026.pdf#page=2"
                 },
                 {
                   "type": "GLTFObject",
                   "model_url": "UBC_Susc_0_0300.gltf",
                   "display_name": "0.03 SI",
                   "include": true,
                   "displayed": true,
                   "reference": "https://sarigbasis.pir.sa.gov.au/WebtopEw/ws/samref/sarig1/image/DDD/GDP00026.pdf#page=2"
                 },
                 {
                   "type": "GLTFObject",
                   "model_url": "UBC_Susc_0_0400.gltf",
                   "display_name": "0.04 SI",
                   "include": true,
                   "displayed": true,
                   "reference": "https://sarigbasis.pir.sa.gov.au/WebtopEw/ws/samref/sarig1/image/DDD/GDP00026.pdf#page=2"
                 },
                 {
                   "type": "GLTFObject",
                   "model_url": "UBC_Susc_0_0500.gltf",
                   "display_name": "0.05 SI",
                   "include": true,
                   "displayed": true,
                   "reference": "https://sarigbasis.pir.sa.gov.au/WebtopEw/ws/samref/sarig1/image/DDD/GDP00026.pdf#page=2"
                 },
                 {
                   "type": "GLTFObject",
                   "model_url": "UBC_Susc_0_0600.gltf",
                   "display_name": "0.06 SI",
                   "include": true,
                   "displayed": true,
                   "reference": "https://sarigbasis.pir.sa.gov.au/WebtopEw/ws/samref/sarig1/image/DDD/GDP00026.pdf#page=2"
                 }
              ],
              "Ammaroodinna Yoolperlunna Faults": [
                 {
                   "type": "GLTFObject",
                   "model_url": "Faults_Ammaroodinna_Yoolperlunna_0.gltf",
                   "display_name": "Fault 1",
                   "include": true,
                   "displayed": true,
                   "reference": "https://sarigbasis.pir.sa.gov.au/WebtopEw/ws/samref/sarig1/image/DDD/GDP00026.pdf#page=2"
                 },
                 {
                   "type": "GLTFObject",
                   "model_url": "Faults_Ammaroodinna_Yoolperlunna_1.gltf",
                   "display_name": "Fault 2",
                   "include": true,
                   "displayed": true,
                   "reference": "https://sarigbasis.pir.sa.gov.au/WebtopEw/ws/samref/sarig1/image/DDD/GDP00026.pdf#page=2"
                 },
                 {
                   "type": "GLTFObject",
                   "model_url": "Faults_Ammaroodinna_Yoolperlunna_2.gltf",
                   "display_name": "Fault 3",
                   "include": true,
                   "displayed": true,
                   "reference": "https://sarigbasis.pir.sa.gov.au/WebtopEw/ws/samref/sarig1/image/DDD/GDP00026.pdf#page=2"
                 },
                 {
                   "type": "GLTFObject",
                   "model_url": "Faults_Ammaroodinna_Yoolperlunna_3.gltf",
                   "display_name": "Fault 4",
                   "include": true,
                   "displayed": true,
                   "reference": "https://sarigbasis.pir.sa.gov.au/WebtopEw/ws/samref/sarig1/image/DDD/GDP00026.pdf#page=2"
                 },
                 {
                   "type": "GLTFObject",
                   "model_url": "Faults_Ammaroodinna_Yoolperlunna_4.gltf",
                   "display_name": "Fault 5",
                   "include": true,
                   "displayed": true,
                   "reference": "https://sarigbasis.pir.sa.gov.au/WebtopEw/ws/samref/sarig1/image/DDD/GDP00026.pdf#page=2"
                 },
                 {
                   "type": "GLTFObject",
                   "model_url": "Faults_Ammaroodinna_Yoolperlunna_5.gltf",
                   "display_name": "Fault 6",
                   "include": true,
                   "displayed": true,
                   "reference": "https://sarigbasis.pir.sa.gov.au/WebtopEw/ws/samref/sarig1/image/DDD/GDP00026.pdf#page=2"
                 },
                 {
                   "type": "GLTFObject",
                   "model_url": "Faults_Ammaroodinna_Yoolperlunna_6.gltf",
                   "display_name": "Fault 7",
                   "include": true,
                   "displayed": true,
                   "reference": "https://sarigbasis.pir.sa.gov.au/WebtopEw/ws/samref/sarig1/image/DDD/GDP00026.pdf#page=2"
                 },
                 {
                   "type": "GLTFObject",
                   "model_url": "Faults_Ammaroodinna_Yoolperlunna_7.gltf",
                   "display_name": "Fault 8",
                   "include": true,
                   "displayed": true,
                   "reference": "https://sarigbasis.pir.sa.gov.au/WebtopEw/ws/samref/sarig1/image/DDD/GDP00026.pdf#page=2"
                 }
              ],
              "Middle Bore Ridge Faults": [
                 {
                   "type": "GLTFObject",
                   "model_url": "Faults_MiddleBoreRidge_0.gltf",
                   "display_name": "Fault 1",
                   "include": true,
                   "displayed": true,
                   "reference": "https://sarigbasis.pir.sa.gov.au/WebtopEw/ws/samref/sarig1/image/DDD/GDP00026.pdf#page=2"
                 },
                 {
                   "type": "GLTFObject",
                   "model_url": "Faults_MiddleBoreRidge_1.gltf",
                   "display_name": "Fault 2",
                   "include": true,
                   "displayed": true,
                   "reference": "https://sarigbasis.pir.sa.gov.au/WebtopEw/ws/samref/sarig1/image/DDD/GDP00026.pdf#page=2"
                 }
              ],
              "Musgrave Block Faults": [
                 {
                   "type": "GLTFObject",
                   "model_url": "Faults_MusgraveBlock_0.gltf",
                   "display_name": "Fault 1",
                   "include": true,
                   "displayed": true,
                   "reference": "https://sarigbasis.pir.sa.gov.au/WebtopEw/ws/samref/sarig1/image/DDD/GDP00026.pdf#page=2"
                 },
                 {
                   "type": "GLTFObject",
                   "model_url": "Faults_MusgraveBlock_1.gltf",
                   "display_name": "Fault 2",
                   "include": true,
                   "displayed": true,
                   "reference": "https://sarigbasis.pir.sa.gov.au/WebtopEw/ws/samref/sarig1/image/DDD/GDP00026.pdf#page=2"
                 }
              ],
              "Wintinna Trough Faults": [
                 {
                   "type": "GLTFObject",
                   "model_url": "Faults_WintinnaTrough_0.gltf",
                   "display_name": "Fault 1",
                   "include": true,
                   "displayed": true,
                   "reference": "https://sarigbasis.pir.sa.gov.au/WebtopEw/ws/samref/sarig1/image/DDD/GDP00026.pdf#page=2"
                 },
                 {
                   "type": "GLTFObject",
                   "model_url": "Faults_WintinnaTrough_1.gltf",
                   "display_name": "Fault 2",
                   "include": true,
                   "displayed": true,
                   "reference": "https://sarigbasis.pir.sa.gov.au/WebtopEw/ws/samref/sarig1/image/DDD/GDP00026.pdf#page=2"
                 }
               ],
"Boreholes": [
{
                "popup_info": {
                    "href": [
                        {
                            "label": "WFS URL",
                            "URL": "https://sarigdata.pir.sa.gov.au/nvcl/resource/feature/PIRSA/borehole/130579"
                        },
                        {
                            "label": "AuScope URL",
                            "URL": "http://portal.auscope.org/portal/gmap.html?s=XQAAAQDvv4IBAAAAAAAAAD3vvojvvonvvqI3LO+/vzc7CwN/aO++rO+/kndiBe+/pCbvvoBgTu+/te++qk/vv73vvpDvvq9SEu+/pO++h++/uu+/uDIILSAM77+u776qIu+/oe++sg/vvqLvv6/vv6cWERE5Be+/se++sD1877+Qbn3vvrfvvqXvvpEyAmUy776DX2Xvv7Tvv4Am77+iV0jvvrt077+k776B77+TS0fvvqDvvqXvv5Yy77++776l77+/NTkZawHvv7Tvv7Tvv6/vvol0SUwH776iG++/g+++lTLvvojvv5rvvoVVOu+/tRBA77+Ff3RL77+nAGlRck9VQe++qW/vvrhhFe+/gkhQYWXvvqIj776NR+++j++/uEkYPH8f776ndxIb776dOShCPnlxQw4CaO++u0/vv7vvvrLvv598A++/kO++g3BtPWrvv5Pvv6M2776AZGvvvrgudHoC77+tbxzvvqt/Lw1hKgLvvqjvv5Lvv4rvvoRECH9kbGs/77+NcRoQfe++rO+/o+++rO++lu+/pe+/ikMT776CGe++gnvvv43vvqp/PGnvv6jvv6LvvqMz776577+k776I776ZZEnvv6M577+o776SVCzvvo/vvrEjN+++lmrvvrYAVgMj77+IEEQL776OBBV/77+0T++/lSbvvp9Hfe+/qu+/pVXvv6g2UBBp77+y77+rW++/gO+/jBLvv6Hvv53vv5/vvqEt77+o77+rNTMaNBnvv5Ai776777+DKjtC77+y77+w77++77+5776wEA==&v=4"
                        }
                    ],
                    "location": "134.245 -27.169",
                    "inclinationType": "vertical",
                    "dateOfDrilling": "1981-11-22",
                    "title": "EOB 2",
                    "coreCustodian": null,
                    "drillingMethod": "Diamond Bit - Coring Rotary - Percussion",
                    "elevation": "240.610",
                    "driller": null,
                    "coredInterval": null,
                    "startPoint": "natural ground surface"
                },
                "display_name": "EOB 2",
                "model_url": "Borehole_EOB_2.gltf",
                "type": "GLTFObject",
                "3dobject_label": "borehole-EOB_2",
                "displayed": true,
                "position": [
                    1020021.3611053994,
                    6983946.857116169,
                    240.61
                ],
                "include": true
            },
            {
                "popup_info": {
                    "href": [
                        {
                            "label": "WFS URL",
                            "URL": "https://sarigdata.pir.sa.gov.au/nvcl/resource/feature/PIRSA/borehole/130581"
                        },
                        {
                            "label": "AuScope URL",
                            "URL": "http://portal.auscope.org/portal/gmap.html?s=XQAAAQDvv4IBAAAAAAAAAD3vvojvvonvvqI3LO+/vzc7CwN/aO++rO+/kndiBe+/pCbvvoBgTu+/te++qk/vv73vvpDvvq9SEu+/pO++h++/uu+/uDIILSAM77+u776qIu+/oe++sg/vvqLvv6/vv6cWERE5Be+/se++sD1877+Qbn3vvrfvvqXvvpEyAmUy776DX2Xvv7Tvv4Am77+iV0jvvrt077+k776B77+TS0fvvqDvvqXvv5Yy77++776l77+/NTkZawHvv7Tvv7Tvv6/vvol0SUwH776iG++/g+++lTLvvojvv5rvvoVVOu+/tRBA77+Ff3RL77+nAGlRck9VQe++qW/vvrhhFe+/gkhQYWXvvqIj776NR+++j++/uEkYPH8f776ndxIb776dOShCPnlxQw4CaO++u0/vv7vvvrLvv598A++/kO++g3BtPWrvv5Pvv6M2776AZGvvvrgudHoC77+tbxzvvqt/Lw1hKgLvvqjvv5Lvv4rvvoRECH9kbGs/77+NcRoQfe++rO+/o+++rO++lu+/pe+/ikMT776CGe++gnvvv43vvqp/PGnvv6jvv6LvvqMz776577+k776I776ZZEnvv6M577+o776SVCzvvo/vvrEjN+++lmrvvrYAVgMj77+IEEQL776OBBV/77+0T++/lSbvvp9Hfe+/qu+/pVXvv6g2UBBp77+y77+rW++/gO+/jBLvv6Hvv53vv5/vvqEt77+o77+rNTMaNBnvv5Ai776777+DKjtC77+y77+w77++77+5776wEA==&v=4"
                        }
                    ],
                    "location": "133.839 -27.585",
                    "inclinationType": "vertical",
                    "dateOfDrilling": "1983-04-08",
                    "title": "COMALCO SH 2",
                    "coreCustodian": null,
                    "drillingMethod": "Rotary",
                    "elevation": "291.700",
                    "driller": null,
                    "coredInterval": null,
                    "startPoint": "natural ground surface"
                },
                "display_name": "COMALCO SH 2",
                "model_url": "Borehole_COMALCO_SH_2.gltf",
                "type": "GLTFObject",
                "3dobject_label": "borehole-COMALCO_SH_2",
                "displayed": true,
                "position": [
                    977968.5450468571,
                    6939444.6186246835,
                    291.7
                ],
                "include": true
            },
            {
                "popup_info": {
                    "href": [
                        {
                            "label": "WFS URL",
                            "URL": "https://sarigdata.pir.sa.gov.au/nvcl/resource/feature/PIRSA/borehole/130582"
                        },
                        {
                            "label": "AuScope URL",
                            "URL": "http://portal.auscope.org/portal/gmap.html?s=XQAAAQDvv4IBAAAAAAAAAD3vvojvvonvvqI3LO+/vzc7CwN/aO++rO+/kndiBe+/pCbvvoBgTu+/te++qk/vv73vvpDvvq9SEu+/pO++h++/uu+/uDIILSAM77+u776qIu+/oe++sg/vvqLvv6/vv6cWERE5Be+/se++sD1877+Qbn3vvrfvvqXvvpEyAmUy776DX2Xvv7Tvv4Am77+iV0jvvrt077+k776B77+TS0fvvqDvvqXvv5Yy77++776l77+/NTkZawHvv7Tvv7Tvv6/vvol0SUwH776iG++/g+++lTLvvojvv5rvvoVVOu+/tRBA77+Ff3RL77+nAGlRck9VQe++qW/vvrhhFe+/gkhQYWXvvqIj776NR+++j++/uEkYPH8f776ndxIb776dOShCPnlxQw4CaO++u0/vv7vvvrLvv598A++/kO++g3BtPWrvv5Pvv6M2776AZGvvvrgudHoC77+tbxzvvqt/Lw1hKgLvvqjvv5Lvv4rvvoRECH9kbGs/77+NcRoQfe++rO+/o+++rO++lu+/pe+/ikMT776CGe++gnvvv43vvqp/PGnvv6jvv6LvvqMz776577+k776I776ZZEnvv6M577+o776SVCzvvo/vvrEjN+++lmrvvrYAVgMj77+IEEQL776OBBV/77+0T++/lSbvvp9Hfe+/qu+/pVXvv6g2UBBp77+y77+rW++/gO+/jBLvv6Hvv53vv5/vvqEt77+o77+rNTMaNBnvv5Ai776777+DKjtC77+y77+w77++77+5776wEA==&v=4"
                        }
                    ],
                    "location": "133.780 -27.629",
                    "inclinationType": "vertical",
                    "dateOfDrilling": "1983-04-11",
                    "title": "COMALCO SH 3",
                    "coreCustodian": null,
                    "drillingMethod": "Rotary",
                    "elevation": " 0.000",
                    "driller": null,
                    "coredInterval": null,
                    "startPoint": "natural ground surface"
                },
                "display_name": "COMALCO SH 3",
                "model_url": "Borehole_COMALCO_SH_3.gltf",
                "type": "GLTFObject",
                "3dobject_label": "borehole-COMALCO_SH_3",
                "displayed": true,
                "position": [
                    971849.6443499702,
                    6934804.330075145,
                    0.0
                ],
                "include": true
            },
            {
                "popup_info": {
                    "href": [
                        {
                            "label": "WFS URL",
                            "URL": "https://sarigdata.pir.sa.gov.au/nvcl/resource/feature/PIRSA/borehole/130583"
                        },
                        {
                            "label": "AuScope URL",
                            "URL": "http://portal.auscope.org/portal/gmap.html?s=XQAAAQDvv4IBAAAAAAAAAD3vvojvvonvvqI3LO+/vzc7CwN/aO++rO+/kndiBe+/pCbvvoBgTu+/te++qk/vv73vvpDvvq9SEu+/pO++h++/uu+/uDIILSAM77+u776qIu+/oe++sg/vvqLvv6/vv6cWERE5Be+/se++sD1877+Qbn3vvrfvvqXvvpEyAmUy776DX2Xvv7Tvv4Am77+iV0jvvrt077+k776B77+TS0fvvqDvvqXvv5Yy77++776l77+/NTkZawHvv7Tvv7Tvv6/vvol0SUwH776iG++/g+++lTLvvojvv5rvvoVVOu+/tRBA77+Ff3RL77+nAGlRck9VQe++qW/vvrhhFe+/gkhQYWXvvqIj776NR+++j++/uEkYPH8f776ndxIb776dOShCPnlxQw4CaO++u0/vv7vvvrLvv598A++/kO++g3BtPWrvv5Pvv6M2776AZGvvvrgudHoC77+tbxzvvqt/Lw1hKgLvvqjvv5Lvv4rvvoRECH9kbGs/77+NcRoQfe++rO+/o+++rO++lu+/pe+/ikMT776CGe++gnvvv43vvqp/PGnvv6jvv6LvvqMz776577+k776I776ZZEnvv6M577+o776SVCzvvo/vvrEjN+++lmrvvrYAVgMj77+IEEQL776OBBV/77+0T++/lSbvvp9Hfe+/qu+/pVXvv6g2UBBp77+y77+rW++/gO+/jBLvv6Hvv53vv5/vvqEt77+o77+rNTMaNBnvv5Ai776777+DKjtC77+y77+w77++77+5776wEA==&v=4"
                        }
                    ],
                    "location": "133.748 -27.651",
                    "inclinationType": "vertical",
                    "dateOfDrilling": "1983-04-12",
                    "title": "COMALCO SH 4",
                    "coreCustodian": null,
                    "drillingMethod": "Rotary",
                    "elevation": "268.000",
                    "driller": null,
                    "coredInterval": null,
                    "startPoint": "natural ground surface"
                },
                "display_name": "COMALCO SH 4",
                "model_url": "Borehole_COMALCO_SH_4.gltf",
                "type": "GLTFObject",
                "3dobject_label": "borehole-COMALCO_SH_4",
                "displayed": true,
                "position": [
                    968620.9672398102,
                    6932378.104511566,
                    268.0
                ],
                "include": true
            },
            {
                "popup_info": {
                    "href": [
                        {
                            "label": "WFS URL",
                            "URL": "https://sarigdata.pir.sa.gov.au/nvcl/resource/feature/PIRSA/borehole/130584"
                        },
                        {
                            "label": "AuScope URL",
                            "URL": "http://portal.auscope.org/portal/gmap.html?s=XQAAAQDvv4IBAAAAAAAAAD3vvojvvonvvqI3LO+/vzc7CwN/aO++rO+/kndiBe+/pCbvvoBgTu+/te++qk/vv73vvpDvvq9SEu+/pO++h++/uu+/uDIILSAM77+u776qIu+/oe++sg/vvqLvv6/vv6cWERE5Be+/se++sD1877+Qbn3vvrfvvqXvvpEyAmUy776DX2Xvv7Tvv4Am77+iV0jvvrt077+k776B77+TS0fvvqDvvqXvv5Yy77++776l77+/NTkZawHvv7Tvv7Tvv6/vvol0SUwH776iG++/g+++lTLvvojvv5rvvoVVOu+/tRBA77+Ff3RL77+nAGlRck9VQe++qW/vvrhhFe+/gkhQYWXvvqIj776NR+++j++/uEkYPH8f776ndxIb776dOShCPnlxQw4CaO++u0/vv7vvvrLvv598A++/kO++g3BtPWrvv5Pvv6M2776AZGvvvrgudHoC77+tbxzvvqt/Lw1hKgLvvqjvv5Lvv4rvvoRECH9kbGs/77+NcRoQfe++rO+/o+++rO++lu+/pe+/ikMT776CGe++gnvvv43vvqp/PGnvv6jvv6LvvqMz776577+k776I776ZZEnvv6M577+o776SVCzvvo/vvrEjN+++lmrvvrYAVgMj77+IEEQL776OBBV/77+0T++/lSbvvp9Hfe+/qu+/pVXvv6g2UBBp77+y77+rW++/gO+/jBLvv6Hvv53vv5/vvqEt77+o77+rNTMaNBnvv5Ai776777+DKjtC77+y77+w77++77+5776wEA==&v=4"
                        }
                    ],
                    "location": "133.718 -27.673",
                    "inclinationType": "vertical",
                    "dateOfDrilling": "1983-04-13",
                    "title": "COMALCO SH 5",
                    "coreCustodian": null,
                    "drillingMethod": "Rotary",
                    "elevation": "265.100",
                    "driller": null,
                    "coredInterval": null,
                    "startPoint": "natural ground surface"
                },
                "display_name": "COMALCO SH 5",
                "model_url": "Borehole_COMALCO_SH_5.gltf",
                "type": "GLTFObject",
                "3dobject_label": "borehole-COMALCO_SH_5",
                "displayed": true,
                "position": [
                    965606.5762948157,
                    6930109.213865984,
                    265.1
                ],
                "include": true
            },
            {
                "popup_info": {
                    "href": [
                        {
                            "label": "WFS URL",
                            "URL": "https://sarigdata.pir.sa.gov.au/nvcl/resource/feature/PIRSA/borehole/130585"
                        },
                        {
                            "label": "AuScope URL",
                            "URL": "http://portal.auscope.org/portal/gmap.html?s=XQAAAQDvv4IBAAAAAAAAAD3vvojvvonvvqI3LO+/vzc7CwN/aO++rO+/kndiBe+/pCbvvoBgTu+/te++qk/vv73vvpDvvq9SEu+/pO++h++/uu+/uDIILSAM77+u776qIu+/oe++sg/vvqLvv6/vv6cWERE5Be+/se++sD1877+Qbn3vvrfvvqXvvpEyAmUy776DX2Xvv7Tvv4Am77+iV0jvvrt077+k776B77+TS0fvvqDvvqXvv5Yy77++776l77+/NTkZawHvv7Tvv7Tvv6/vvol0SUwH776iG++/g+++lTLvvojvv5rvvoVVOu+/tRBA77+Ff3RL77+nAGlRck9VQe++qW/vvrhhFe+/gkhQYWXvvqIj776NR+++j++/uEkYPH8f776ndxIb776dOShCPnlxQw4CaO++u0/vv7vvvrLvv598A++/kO++g3BtPWrvv5Pvv6M2776AZGvvvrgudHoC77+tbxzvvqt/Lw1hKgLvvqjvv5Lvv4rvvoRECH9kbGs/77+NcRoQfe++rO+/o+++rO++lu+/pe+/ikMT776CGe++gnvvv43vvqp/PGnvv6jvv6LvvqMz776577+k776I776ZZEnvv6M577+o776SVCzvvo/vvrEjN+++lmrvvrYAVgMj77+IEEQL776OBBV/77+0T++/lSbvvp9Hfe+/qu+/pVXvv6g2UBBp77+y77+rW++/gO+/jBLvv6Hvv53vv5/vvqEt77+o77+rNTMaNBnvv5Ai776777+DKjtC77+y77+w77++77+5776wEA==&v=4"
                        }
                    ],
                    "location": "133.776 -27.509",
                    "inclinationType": "vertical",
                    "dateOfDrilling": "1983-04-19",
                    "title": "COMALCO SH 6",
                    "coreCustodian": null,
                    "drillingMethod": "Rotary",
                    "elevation": "293.400",
                    "driller": null,
                    "coredInterval": null,
                    "startPoint": "natural ground surface"
                },
                "display_name": "COMALCO SH 6",
                "model_url": "Borehole_COMALCO_SH_6.gltf",
                "type": "GLTFObject",
                "3dobject_label": "borehole-COMALCO_SH_6",
                "displayed": true,
                "position": [
                    972011.2721373867,
                    6948112.51583606,
                    293.4
                ],
                "include": true
            },
            {
                "popup_info": {
                    "href": [
                        {
                            "label": "WFS URL",
                            "URL": "https://sarigdata.pir.sa.gov.au/nvcl/resource/feature/PIRSA/borehole/130586"
                        },
                        {
                            "label": "AuScope URL",
                            "URL": "http://portal.auscope.org/portal/gmap.html?s=XQAAAQDvv4IBAAAAAAAAAD3vvojvvonvvqI3LO+/vzc7CwN/aO++rO+/kndiBe+/pCbvvoBgTu+/te++qk/vv73vvpDvvq9SEu+/pO++h++/uu+/uDIILSAM77+u776qIu+/oe++sg/vvqLvv6/vv6cWERE5Be+/se++sD1877+Qbn3vvrfvvqXvvpEyAmUy776DX2Xvv7Tvv4Am77+iV0jvvrt077+k776B77+TS0fvvqDvvqXvv5Yy77++776l77+/NTkZawHvv7Tvv7Tvv6/vvol0SUwH776iG++/g+++lTLvvojvv5rvvoVVOu+/tRBA77+Ff3RL77+nAGlRck9VQe++qW/vvrhhFe+/gkhQYWXvvqIj776NR+++j++/uEkYPH8f776ndxIb776dOShCPnlxQw4CaO++u0/vv7vvvrLvv598A++/kO++g3BtPWrvv5Pvv6M2776AZGvvvrgudHoC77+tbxzvvqt/Lw1hKgLvvqjvv5Lvv4rvvoRECH9kbGs/77+NcRoQfe++rO+/o+++rO++lu+/pe+/ikMT776CGe++gnvvv43vvqp/PGnvv6jvv6LvvqMz776577+k776I776ZZEnvv6M577+o776SVCzvvo/vvrEjN+++lmrvvrYAVgMj77+IEEQL776OBBV/77+0T++/lSbvvp9Hfe+/qu+/pVXvv6g2UBBp77+y77+rW++/gO+/jBLvv6Hvv53vv5/vvqEt77+o77+rNTMaNBnvv5Ai776777+DKjtC77+y77+w77++77+5776wEA==&v=4"
                        }
                    ],
                    "location": "133.695 -27.412",
                    "inclinationType": "vertical",
                    "dateOfDrilling": "1983-04-20",
                    "title": "COMALCO SH 7",
                    "coreCustodian": null,
                    "drillingMethod": "Rotary",
                    "elevation": "298.200",
                    "driller": null,
                    "coredInterval": null,
                    "startPoint": "natural ground surface"
                },
                "display_name": "COMALCO SH 7",
                "model_url": "Borehole_COMALCO_SH_7.gltf",
                "type": "GLTFObject",
                "3dobject_label": "borehole-COMALCO_SH_7",
                "displayed": true,
                "position": [
                    964362.3517098825,
                    6959189.953997016,
                    298.2
                ],
                "include": true
            },
            {
                "popup_info": {
                    "href": [
                        {
                            "label": "WFS URL",
                            "URL": "https://sarigdata.pir.sa.gov.au/nvcl/resource/feature/PIRSA/borehole/130587"
                        },
                        {
                            "label": "AuScope URL",
                            "URL": "http://portal.auscope.org/portal/gmap.html?s=XQAAAQDvv4IBAAAAAAAAAD3vvojvvonvvqI3LO+/vzc7CwN/aO++rO+/kndiBe+/pCbvvoBgTu+/te++qk/vv73vvpDvvq9SEu+/pO++h++/uu+/uDIILSAM77+u776qIu+/oe++sg/vvqLvv6/vv6cWERE5Be+/se++sD1877+Qbn3vvrfvvqXvvpEyAmUy776DX2Xvv7Tvv4Am77+iV0jvvrt077+k776B77+TS0fvvqDvvqXvv5Yy77++776l77+/NTkZawHvv7Tvv7Tvv6/vvol0SUwH776iG++/g+++lTLvvojvv5rvvoVVOu+/tRBA77+Ff3RL77+nAGlRck9VQe++qW/vvrhhFe+/gkhQYWXvvqIj776NR+++j++/uEkYPH8f776ndxIb776dOShCPnlxQw4CaO++u0/vv7vvvrLvv598A++/kO++g3BtPWrvv5Pvv6M2776AZGvvvrgudHoC77+tbxzvvqt/Lw1hKgLvvqjvv5Lvv4rvvoRECH9kbGs/77+NcRoQfe++rO+/o+++rO++lu+/pe+/ikMT776CGe++gnvvv43vvqp/PGnvv6jvv6LvvqMz776577+k776I776ZZEnvv6M577+o776SVCzvvo/vvrEjN+++lmrvvrYAVgMj77+IEEQL776OBBV/77+0T++/lSbvvp9Hfe+/qu+/pVXvv6g2UBBp77+y77+rW++/gO+/jBLvv6Hvv53vv5/vvqEt77+o77+rNTMaNBnvv5Ai776777+DKjtC77+y77+w77++77+5776wEA==&v=4"
                        }
                    ],
                    "location": "133.628 -27.322",
                    "inclinationType": "vertical",
                    "dateOfDrilling": "1983-04-21",
                    "title": "COMALCO SH 8",
                    "coreCustodian": null,
                    "drillingMethod": "Rotary",
                    "elevation": "322.500",
                    "driller": null,
                    "coredInterval": null,
                    "startPoint": "natural ground surface"
                },
                "display_name": "COMALCO SH 8",
                "model_url": "Borehole_COMALCO_SH_8.gltf",
                "type": "GLTFObject",
                "3dobject_label": "borehole-COMALCO_SH_8",
                "displayed": true,
                "position": [
                    958104.0998343759,
                    6969362.045445094,
                    322.5
                ],
                "include": true
            },
            {
                "popup_info": {
                    "href": [
                        {
                            "label": "WFS URL",
                            "URL": "https://sarigdata.pir.sa.gov.au/nvcl/resource/feature/PIRSA/borehole/130588"
                        },
                        {
                            "label": "AuScope URL",
                            "URL": "http://portal.auscope.org/portal/gmap.html?s=XQAAAQDvv4IBAAAAAAAAAD3vvojvvonvvqI3LO+/vzc7CwN/aO++rO+/kndiBe+/pCbvvoBgTu+/te++qk/vv73vvpDvvq9SEu+/pO++h++/uu+/uDIILSAM77+u776qIu+/oe++sg/vvqLvv6/vv6cWERE5Be+/se++sD1877+Qbn3vvrfvvqXvvpEyAmUy776DX2Xvv7Tvv4Am77+iV0jvvrt077+k776B77+TS0fvvqDvvqXvv5Yy77++776l77+/NTkZawHvv7Tvv7Tvv6/vvol0SUwH776iG++/g+++lTLvvojvv5rvvoVVOu+/tRBA77+Ff3RL77+nAGlRck9VQe++qW/vvrhhFe+/gkhQYWXvvqIj776NR+++j++/uEkYPH8f776ndxIb776dOShCPnlxQw4CaO++u0/vv7vvvrLvv598A++/kO++g3BtPWrvv5Pvv6M2776AZGvvvrgudHoC77+tbxzvvqt/Lw1hKgLvvqjvv5Lvv4rvvoRECH9kbGs/77+NcRoQfe++rO+/o+++rO++lu+/pe+/ikMT776CGe++gnvvv43vvqp/PGnvv6jvv6LvvqMz776577+k776I776ZZEnvv6M577+o776SVCzvvo/vvrEjN+++lmrvvrYAVgMj77+IEEQL776OBBV/77+0T++/lSbvvp9Hfe+/qu+/pVXvv6g2UBBp77+y77+rW++/gO+/jBLvv6Hvv53vv5/vvqEt77+o77+rNTMaNBnvv5Ai776777+DKjtC77+y77+w77++77+5776wEA==&v=4"
                        }
                    ],
                    "location": "133.923 -27.677",
                    "inclinationType": "vertical",
                    "dateOfDrilling": "1983-04-24",
                    "title": "COMALCO SH 9",
                    "coreCustodian": null,
                    "drillingMethod": "Rotary",
                    "elevation": "303.800",
                    "driller": null,
                    "coredInterval": null,
                    "startPoint": "natural ground surface"
                },
                "display_name": "COMALCO SH 9",
                "model_url": "Borehole_COMALCO_SH_9.gltf",
                "type": "GLTFObject",
                "3dobject_label": "borehole-COMALCO_SH_9",
                "displayed": true,
                "position": [
                    985793.7060730869,
                    6928878.928369226,
                    303.8
                ],
                "include": true
            },
            {
                "popup_info": {
                    "href": [
                        {
                            "label": "WFS URL",
                            "URL": "https://sarigdata.pir.sa.gov.au/nvcl/resource/feature/PIRSA/borehole/130589"
                        },
                        {
                            "label": "AuScope URL",
                            "URL": "http://portal.auscope.org/portal/gmap.html?s=XQAAAQDvv4IBAAAAAAAAAD3vvojvvonvvqI3LO+/vzc7CwN/aO++rO+/kndiBe+/pCbvvoBgTu+/te++qk/vv73vvpDvvq9SEu+/pO++h++/uu+/uDIILSAM77+u776qIu+/oe++sg/vvqLvv6/vv6cWERE5Be+/se++sD1877+Qbn3vvrfvvqXvvpEyAmUy776DX2Xvv7Tvv4Am77+iV0jvvrt077+k776B77+TS0fvvqDvvqXvv5Yy77++776l77+/NTkZawHvv7Tvv7Tvv6/vvol0SUwH776iG++/g+++lTLvvojvv5rvvoVVOu+/tRBA77+Ff3RL77+nAGlRck9VQe++qW/vvrhhFe+/gkhQYWXvvqIj776NR+++j++/uEkYPH8f776ndxIb776dOShCPnlxQw4CaO++u0/vv7vvvrLvv598A++/kO++g3BtPWrvv5Pvv6M2776AZGvvvrgudHoC77+tbxzvvqt/Lw1hKgLvvqjvv5Lvv4rvvoRECH9kbGs/77+NcRoQfe++rO+/o+++rO++lu+/pe+/ikMT776CGe++gnvvv43vvqp/PGnvv6jvv6LvvqMz776577+k776I776ZZEnvv6M577+o776SVCzvvo/vvrEjN+++lmrvvrYAVgMj77+IEEQL776OBBV/77+0T++/lSbvvp9Hfe+/qu+/pVXvv6g2UBBp77+y77+rW++/gO+/jBLvv6Hvv53vv5/vvqEt77+o77+rNTMaNBnvv5Ai776777+DKjtC77+y77+w77++77+5776wEA==&v=4"
                        }
                    ],
                    "location": "134.003 -27.771",
                    "inclinationType": "vertical",
                    "dateOfDrilling": "1983-04-25",
                    "title": "COMALCO SH 10",
                    "coreCustodian": null,
                    "drillingMethod": "Rotary",
                    "elevation": "314.300",
                    "driller": null,
                    "coredInterval": null,
                    "startPoint": "natural ground surface"
                },
                "display_name": "COMALCO SH 10",
                "model_url": "Borehole_COMALCO_SH_10.gltf",
                "type": "GLTFObject",
                "3dobject_label": "borehole-COMALCO_SH_10",
                "displayed": true,
                "position": [
                    993273.7557468328,
                    6918151.242249329,
                    314.3
                ],
                "include": true
            },
            {
                "popup_info": {
                    "href": [
                        {
                            "label": "WFS URL",
                            "URL": "https://sarigdata.pir.sa.gov.au/nvcl/resource/feature/PIRSA/borehole/130590"
                        },
                        {
                            "label": "AuScope URL",
                            "URL": "http://portal.auscope.org/portal/gmap.html?s=XQAAAQDvv4IBAAAAAAAAAD3vvojvvonvvqI3LO+/vzc7CwN/aO++rO+/kndiBe+/pCbvvoBgTu+/te++qk/vv73vvpDvvq9SEu+/pO++h++/uu+/uDIILSAM77+u776qIu+/oe++sg/vvqLvv6/vv6cWERE5Be+/se++sD1877+Qbn3vvrfvvqXvvpEyAmUy776DX2Xvv7Tvv4Am77+iV0jvvrt077+k776B77+TS0fvvqDvvqXvv5Yy77++776l77+/NTkZawHvv7Tvv7Tvv6/vvol0SUwH776iG++/g+++lTLvvojvv5rvvoVVOu+/tRBA77+Ff3RL77+nAGlRck9VQe++qW/vvrhhFe+/gkhQYWXvvqIj776NR+++j++/uEkYPH8f776ndxIb776dOShCPnlxQw4CaO++u0/vv7vvvrLvv598A++/kO++g3BtPWrvv5Pvv6M2776AZGvvvrgudHoC77+tbxzvvqt/Lw1hKgLvvqjvv5Lvv4rvvoRECH9kbGs/77+NcRoQfe++rO+/o+++rO++lu+/pe+/ikMT776CGe++gnvvv43vvqp/PGnvv6jvv6LvvqMz776577+k776I776ZZEnvv6M577+o776SVCzvvo/vvrEjN+++lmrvvrYAVgMj77+IEEQL776OBBV/77+0T++/lSbvvp9Hfe+/qu+/pVXvv6g2UBBp77+y77+rW++/gO+/jBLvv6Hvv53vv5/vvqEt77+o77+rNTMaNBnvv5Ai776777+DKjtC77+y77+w77++77+5776wEA==&v=4"
                        }
                    ],
                    "location": "133.507 -27.356",
                    "inclinationType": "vertical",
                    "dateOfDrilling": "1983-04-26",
                    "title": "COMALCO SH 11",
                    "coreCustodian": null,
                    "drillingMethod": "Rotary",
                    "elevation": "316.900",
                    "driller": null,
                    "coredInterval": null,
                    "startPoint": "natural ground surface"
                },
                "display_name": "COMALCO SH 11",
                "model_url": "Borehole_COMALCO_SH_11.gltf",
                "type": "GLTFObject",
                "3dobject_label": "borehole-COMALCO_SH_11",
                "displayed": true,
                "position": [
                    946039.5624554569,
                    6966049.309179772,
                    316.9
                ],
                "include": true
            },
            {
                "popup_info": {
                    "href": [
                        {
                            "label": "WFS URL",
                            "URL": "https://sarigdata.pir.sa.gov.au/nvcl/resource/feature/PIRSA/borehole/130592"
                        },
                        {
                            "label": "AuScope URL",
                            "URL": "http://portal.auscope.org/portal/gmap.html?s=XQAAAQDvv4IBAAAAAAAAAD3vvojvvonvvqI3LO+/vzc7CwN/aO++rO+/kndiBe+/pCbvvoBgTu+/te++qk/vv73vvpDvvq9SEu+/pO++h++/uu+/uDIILSAM77+u776qIu+/oe++sg/vvqLvv6/vv6cWERE5Be+/se++sD1877+Qbn3vvrfvvqXvvpEyAmUy776DX2Xvv7Tvv4Am77+iV0jvvrt077+k776B77+TS0fvvqDvvqXvv5Yy77++776l77+/NTkZawHvv7Tvv7Tvv6/vvol0SUwH776iG++/g+++lTLvvojvv5rvvoVVOu+/tRBA77+Ff3RL77+nAGlRck9VQe++qW/vvrhhFe+/gkhQYWXvvqIj776NR+++j++/uEkYPH8f776ndxIb776dOShCPnlxQw4CaO++u0/vv7vvvrLvv598A++/kO++g3BtPWrvv5Pvv6M2776AZGvvvrgudHoC77+tbxzvvqt/Lw1hKgLvvqjvv5Lvv4rvvoRECH9kbGs/77+NcRoQfe++rO+/o+++rO++lu+/pe+/ikMT776CGe++gnvvv43vvqp/PGnvv6jvv6LvvqMz776577+k776I776ZZEnvv6M577+o776SVCzvvo/vvrEjN+++lmrvvrYAVgMj77+IEEQL776OBBV/77+0T++/lSbvvp9Hfe+/qu+/pVXvv6g2UBBp77+y77+rW++/gO+/jBLvv6Hvv53vv5/vvqEt77+o77+rNTMaNBnvv5Ai776777+DKjtC77+y77+w77++77+5776wEA==&v=4"
                        }
                    ],
                    "location": "133.629 -27.408",
                    "inclinationType": "vertical",
                    "dateOfDrilling": "1983-04-28",
                    "title": "COMALCO SH 13",
                    "coreCustodian": null,
                    "drillingMethod": "Rotary",
                    "elevation": "310.800",
                    "driller": null,
                    "coredInterval": null,
                    "startPoint": "natural ground surface"
                },
                "display_name": "COMALCO SH 13",
                "model_url": "Borehole_COMALCO_SH_13.gltf",
                "type": "GLTFObject",
                "3dobject_label": "borehole-COMALCO_SH_13",
                "displayed": true,
                "position": [
                    957851.1989370121,
                    6959874.841767695,
                    310.8
                ],
                "include": true
            },
            {
                "popup_info": {
                    "href": [
                        {
                            "label": "WFS URL",
                            "URL": "https://sarigdata.pir.sa.gov.au/nvcl/resource/feature/PIRSA/borehole/130593"
                        },
                        {
                            "label": "AuScope URL",
                            "URL": "http://portal.auscope.org/portal/gmap.html?s=XQAAAQDvv4IBAAAAAAAAAD3vvojvvonvvqI3LO+/vzc7CwN/aO++rO+/kndiBe+/pCbvvoBgTu+/te++qk/vv73vvpDvvq9SEu+/pO++h++/uu+/uDIILSAM77+u776qIu+/oe++sg/vvqLvv6/vv6cWERE5Be+/se++sD1877+Qbn3vvrfvvqXvvpEyAmUy776DX2Xvv7Tvv4Am77+iV0jvvrt077+k776B77+TS0fvvqDvvqXvv5Yy77++776l77+/NTkZawHvv7Tvv7Tvv6/vvol0SUwH776iG++/g+++lTLvvojvv5rvvoVVOu+/tRBA77+Ff3RL77+nAGlRck9VQe++qW/vvrhhFe+/gkhQYWXvvqIj776NR+++j++/uEkYPH8f776ndxIb776dOShCPnlxQw4CaO++u0/vv7vvvrLvv598A++/kO++g3BtPWrvv5Pvv6M2776AZGvvvrgudHoC77+tbxzvvqt/Lw1hKgLvvqjvv5Lvv4rvvoRECH9kbGs/77+NcRoQfe++rO+/o+++rO++lu+/pe+/ikMT776CGe++gnvvv43vvqp/PGnvv6jvv6LvvqMz776577+k776I776ZZEnvv6M577+o776SVCzvvo/vvrEjN+++lmrvvrYAVgMj77+IEEQL776OBBV/77+0T++/lSbvvp9Hfe+/qu+/pVXvv6g2UBBp77+y77+rW++/gO+/jBLvv6Hvv53vv5/vvqEt77+o77+rNTMaNBnvv5Ai776777+DKjtC77+y77+w77++77+5776wEA==&v=4"
                        }
                    ],
                    "location": "133.649 -27.472",
                    "inclinationType": "vertical",
                    "dateOfDrilling": "1983-04-29",
                    "title": "COMALCO SH 14",
                    "coreCustodian": null,
                    "drillingMethod": "Rotary",
                    "elevation": "292.800",
                    "driller": null,
                    "coredInterval": null,
                    "startPoint": "natural ground surface"
                },
                "display_name": "COMALCO SH 14",
                "model_url": "Borehole_COMALCO_SH_14.gltf",
                "type": "GLTFObject",
                "3dobject_label": "borehole-COMALCO_SH_14",
                "displayed": true,
                "position": [
                    959559.1578963725,
                    6952714.213126646,
                    292.8
                ],
                "include": true
            },
            {
                "popup_info": {
                    "href": [
                        {
                            "label": "WFS URL",
                            "URL": "https://sarigdata.pir.sa.gov.au/nvcl/resource/feature/PIRSA/borehole/130594"
                        },
                        {
                            "label": "AuScope URL",
                            "URL": "http://portal.auscope.org/portal/gmap.html?s=XQAAAQDvv4IBAAAAAAAAAD3vvojvvonvvqI3LO+/vzc7CwN/aO++rO+/kndiBe+/pCbvvoBgTu+/te++qk/vv73vvpDvvq9SEu+/pO++h++/uu+/uDIILSAM77+u776qIu+/oe++sg/vvqLvv6/vv6cWERE5Be+/se++sD1877+Qbn3vvrfvvqXvvpEyAmUy776DX2Xvv7Tvv4Am77+iV0jvvrt077+k776B77+TS0fvvqDvvqXvv5Yy77++776l77+/NTkZawHvv7Tvv7Tvv6/vvol0SUwH776iG++/g+++lTLvvojvv5rvvoVVOu+/tRBA77+Ff3RL77+nAGlRck9VQe++qW/vvrhhFe+/gkhQYWXvvqIj776NR+++j++/uEkYPH8f776ndxIb776dOShCPnlxQw4CaO++u0/vv7vvvrLvv598A++/kO++g3BtPWrvv5Pvv6M2776AZGvvvrgudHoC77+tbxzvvqt/Lw1hKgLvvqjvv5Lvv4rvvoRECH9kbGs/77+NcRoQfe++rO+/o+++rO++lu+/pe+/ikMT776CGe++gnvvv43vvqp/PGnvv6jvv6LvvqMz776577+k776I776ZZEnvv6M577+o776SVCzvvo/vvrEjN+++lmrvvrYAVgMj77+IEEQL776OBBV/77+0T++/lSbvvp9Hfe+/qu+/pVXvv6g2UBBp77+y77+rW++/gO+/jBLvv6Hvv53vv5/vvqEt77+o77+rNTMaNBnvv5Ai776777+DKjtC77+y77+w77++77+5776wEA==&v=4"
                        }
                    ],
                    "location": "133.671 -27.543",
                    "inclinationType": "vertical",
                    "dateOfDrilling": "1983-04-30",
                    "title": "COMALCO SH 15",
                    "coreCustodian": null,
                    "drillingMethod": "Rotary",
                    "elevation": "281.300",
                    "driller": null,
                    "coredInterval": null,
                    "startPoint": "natural ground surface"
                },
                "display_name": "COMALCO SH 15",
                "model_url": "Borehole_COMALCO_SH_15.gltf",
                "type": "GLTFObject",
                "3dobject_label": "borehole-COMALCO_SH_15",
                "displayed": true,
                "position": [
                    961520.2672007043,
                    6944746.048762935,
                    281.3
                ],
                "include": true
            },
            {
                "popup_info": {
                    "href": [
                        {
                            "label": "WFS URL",
                            "URL": "https://sarigdata.pir.sa.gov.au/nvcl/resource/feature/PIRSA/borehole/130595"
                        },
                        {
                            "label": "AuScope URL",
                            "URL": "http://portal.auscope.org/portal/gmap.html?s=XQAAAQDvv4IBAAAAAAAAAD3vvojvvonvvqI3LO+/vzc7CwN/aO++rO+/kndiBe+/pCbvvoBgTu+/te++qk/vv73vvpDvvq9SEu+/pO++h++/uu+/uDIILSAM77+u776qIu+/oe++sg/vvqLvv6/vv6cWERE5Be+/se++sD1877+Qbn3vvrfvvqXvvpEyAmUy776DX2Xvv7Tvv4Am77+iV0jvvrt077+k776B77+TS0fvvqDvvqXvv5Yy77++776l77+/NTkZawHvv7Tvv7Tvv6/vvol0SUwH776iG++/g+++lTLvvojvv5rvvoVVOu+/tRBA77+Ff3RL77+nAGlRck9VQe++qW/vvrhhFe+/gkhQYWXvvqIj776NR+++j++/uEkYPH8f776ndxIb776dOShCPnlxQw4CaO++u0/vv7vvvrLvv598A++/kO++g3BtPWrvv5Pvv6M2776AZGvvvrgudHoC77+tbxzvvqt/Lw1hKgLvvqjvv5Lvv4rvvoRECH9kbGs/77+NcRoQfe++rO+/o+++rO++lu+/pe+/ikMT776CGe++gnvvv43vvqp/PGnvv6jvv6LvvqMz776577+k776I776ZZEnvv6M577+o776SVCzvvo/vvrEjN+++lmrvvrYAVgMj77+IEEQL776OBBV/77+0T++/lSbvvp9Hfe+/qu+/pVXvv6g2UBBp77+y77+rW++/gO+/jBLvv6Hvv53vv5/vvqEt77+o77+rNTMaNBnvv5Ai776777+DKjtC77+y77+w77++77+5776wEA==&v=4"
                        }
                    ],
                    "location": "133.695 -27.610",
                    "inclinationType": "vertical",
                    "dateOfDrilling": "1983-05-01",
                    "title": "COMALCO SH 16",
                    "coreCustodian": null,
                    "drillingMethod": "Rotary",
                    "elevation": "270.800",
                    "driller": null,
                    "coredInterval": null,
                    "startPoint": "natural ground surface"
                },
                "display_name": "COMALCO SH 16",
                "model_url": "Borehole_COMALCO_SH_16.gltf",
                "type": "GLTFObject",
                "3dobject_label": "borehole-COMALCO_SH_16",
                "displayed": true,
                "position": [
                    963541.7341056818,
                    6937172.034691326,
                    270.8
                ],
                "include": true
            },
            {
                "popup_info": {
                    "href": [
                        {
                            "label": "WFS URL",
                            "URL": "https://sarigdata.pir.sa.gov.au/nvcl/resource/feature/PIRSA/borehole/130596"
                        },
                        {
                            "label": "AuScope URL",
                            "URL": "http://portal.auscope.org/portal/gmap.html?s=XQAAAQDvv4IBAAAAAAAAAD3vvojvvonvvqI3LO+/vzc7CwN/aO++rO+/kndiBe+/pCbvvoBgTu+/te++qk/vv73vvpDvvq9SEu+/pO++h++/uu+/uDIILSAM77+u776qIu+/oe++sg/vvqLvv6/vv6cWERE5Be+/se++sD1877+Qbn3vvrfvvqXvvpEyAmUy776DX2Xvv7Tvv4Am77+iV0jvvrt077+k776B77+TS0fvvqDvvqXvv5Yy77++776l77+/NTkZawHvv7Tvv7Tvv6/vvol0SUwH776iG++/g+++lTLvvojvv5rvvoVVOu+/tRBA77+Ff3RL77+nAGlRck9VQe++qW/vvrhhFe+/gkhQYWXvvqIj776NR+++j++/uEkYPH8f776ndxIb776dOShCPnlxQw4CaO++u0/vv7vvvrLvv598A++/kO++g3BtPWrvv5Pvv6M2776AZGvvvrgudHoC77+tbxzvvqt/Lw1hKgLvvqjvv5Lvv4rvvoRECH9kbGs/77+NcRoQfe++rO+/o+++rO++lu+/pe+/ikMT776CGe++gnvvv43vvqp/PGnvv6jvv6LvvqMz776577+k776I776ZZEnvv6M577+o776SVCzvvo/vvrEjN+++lmrvvrYAVgMj77+IEEQL776OBBV/77+0T++/lSbvvp9Hfe+/qu+/pVXvv6g2UBBp77+y77+rW++/gO+/jBLvv6Hvv53vv5/vvqEt77+o77+rNTMaNBnvv5Ai776777+DKjtC77+y77+w77++77+5776wEA==&v=4"
                        }
                    ],
                    "location": "133.687 -27.306",
                    "inclinationType": "vertical",
                    "dateOfDrilling": "1983-05-02",
                    "title": "COMALCO SH 17",
                    "coreCustodian": null,
                    "drillingMethod": "Rotary",
                    "elevation": "318.100",
                    "driller": null,
                    "coredInterval": null,
                    "startPoint": "natural ground surface"
                },
                "display_name": "COMALCO SH 17",
                "model_url": "Borehole_COMALCO_SH_17.gltf",
                "type": "GLTFObject",
                "3dobject_label": "borehole-COMALCO_SH_17",
                "displayed": true,
                "position": [
                    964025.6706795956,
                    6970957.707150323,
                    318.1
                ],
                "include": true
            }
        ]
            },
  "properties": {
    "name": "North Gawler",
    "crs": "EPSG:28352",
    "extent": [868000.0, 1036000.0, 6848000.0, 7016000.0],
    "proj4_defn": "+proj=utm +zone=52 +south +ellps=GRS80 +towgs84=0,0,0,0,0,0,0 +units=m +no_defs"
  }
}